ahadith/__init__.py
ahadith-0.1.1.dist-info/COPYING
ahadith-0.1.1.dist-info/WHEEL
ahadith-0.1.1.dist-info/METADATA
ahadith-0.1.1.dist-info/RECORD
